setup.py
bin/check_connectivity
net_health/__init__.py
net_health/credentials.py
net_health/get_host_ip_nova_manage_script.py
net_health/latency_pollster.py
net_health/monitor_tool.py
net_health/remote_client.py
net_health/utils.py
net_health.egg-info/PKG-INFO
net_health.egg-info/SOURCES.txt
net_health.egg-info/dependency_links.txt
net_health.egg-info/entry_points.txt
net_health.egg-info/not-zip-safe
net_health.egg-info/requires.txt
net_health.egg-info/top_level.txt