Metadata-Version: 1.0
Name: net-health
Version: 0.10
Summary: check network connectivity
Home-page: UNKNOWN
Author: Gilad Zohari
Author-email: gzohari@gmail.com
License: MIT
Platform: UNKNOWN
